di_registry
