Metadata-Version: 2.1
Name: di-registry
Version: 0.5.6
Summary: Simple object registry that can be used for dependency injection and object configuration
Home-page: https://gitlab.com/heingroup/di_registry
Author: Sean Clark
Author-email: sean@v13inc.com
License: MIT
Platform: UNKNOWN
Requires-Python: >=3.6.0
